{
  "className": "SYS_Message",
  "methodName": "removeFollowMouseTip",
  "slug": "SYS_Message.removeFollowMouseTip",
  "docPath": "references/classes/SYS_Message.md",
  "examplePath": "examples/methods/SYS_Message/removeFollowMouseTip.md",
  "kind": "delete",
  "domain": "SYS",
  "requiresDocumentType": null,
  "requiresProject": false,
  "cleanupStrategy": "manual",
  "validationMode": "manual",
  "status": "needs-review",
  "templateName": "review-placeholder",
  "generatedPath": "examples/generated/SYS_Message/removeFollowMouseTip.json",
  "signatures": [
    "removeFollowMouseTip(tip?: string): Promise<void>"
  ],
  "description": "移除跟随鼠标的提示",
  "classSummary": "系统 / 消息通知类",
  "remarks": "移除当前或指定的跟随鼠标的提示",
  "returnSummary": "Promise<void>",
  "params": [
    {
      "name": "tip",
      "type": "string",
      "description": "_（可选）_ 提示内容，如若传入，则仅当当前提示为指定内容时才移除"
    }
  ],
  "exampleNotes": [
    "这个案例由生成器自动补齐为可读草稿，但当前仍建议结合对应类文档做人工复核。"
  ],
  "code": "return await (async function(eda) {\n  const fixtureName = '__codex_example___SYS_Message_removeFollowMouseTip_' + Date.now();\n  const result = await eda.sys_Message.removeFollowMouseTip('Codex example running inside EasyEDA');\n  return { fixtureName, result, needsReview: true };\n})(eda);"
}
